boto4/__init__.py
boto4/cloudformation.py
boto4/secretsmanager.py
boto4_scripts/__init__.py
boto4_scripts/build_lambda_deployment_package.py
boto4-0.0.4.dist-info/LICENSE
boto4-0.0.4.dist-info/METADATA
boto4-0.0.4.dist-info/WHEEL
boto4-0.0.4.dist-info/entry_points.txt
boto4-0.0.4.dist-info/top_level.txt
boto4-0.0.4.dist-info/RECORD
