Metadata-Version: 2.1
Name: boto4
Version: 0.0.4
Summary: Enhanced boto3 functionality (made for my own use)
Home-page: https://github.com/amamparo/boto4
Author: Aaron Mamparo
Author-email: aaronmamparo@gmail.com
License: UNKNOWN
Platform: UNKNOWN
Classifier: Programming Language :: Python :: 3
Classifier: License :: OSI Approved :: MIT License
Classifier: Operating System :: OS Independent
Requires-Python: >= 3.7
Requires-Dist: boto3 (==1.16.4)
Requires-Dist: botocore (==1.19.4)
Requires-Dist: s3transfer (==0.3.3)
Requires-Dist: urllib3 (==1.25.11) ; python_version != "3.4"
Requires-Dist: jmespath (==0.10.0) ; python_version >= "2.6" and python_version not in "3.0, 3.1, 3.2"
Requires-Dist: python-dateutil (==2.8.1) ; python_version >= "2.7" and python_version not in "3.0, 3.1, 3.2"
Requires-Dist: six (==1.15.0) ; python_version >= "2.7" and python_version not in "3.0, 3.1, 3.2"
